{"h_801": {"id": "h_801", "char": "默", "pinyin": "mò", "level": 3, "stroke": 16, "example": "沉默", "frequency": 801, "confusingChars": {"easy": ["黑", "犬"], "medium": ["黑", "墨"], "hard": ["墨", "莫"]}}, "h_802": {"id": "h_802", "char": "沟", "pinyin": "gōu", "level": 3, "stroke": 7, "example": "水沟", "frequency": 802, "confusingChars": {"easy": ["水", "勾"], "medium": ["勾", "钩"], "hard": ["购", "构"]}}, "h_803": {"id": "h_803", "char": "绳", "pinyin": "shéng", "level": 3, "stroke": 11, "example": "绳子", "frequency": 803, "confusingChars": {"easy": ["丝", "口"], "medium": ["蝇", "纯"], "hard": ["蝇", "省"]}}, "h_804": {"id": "h_804", "char": "断", "pinyin": "duàn", "level": 3, "stroke": 11, "example": "断开", "frequency": 804, "confusingChars": {"easy": ["米", "斤"], "medium": ["继", "昕"], "hard": ["段", "继"]}}, "h_805": {"id": "h_805", "char": "瓶", "pinyin": "píng", "level": 3, "stroke": 10, "example": "瓶子", "frequency": 805, "confusingChars": {"easy": ["瓦", "并"], "medium": ["拼", "屏"], "hard": ["平", "苹"]}}, "h_806": {"id": "h_806", "char": "显", "pinyin": "xiǎn", "level": 3, "stroke": 9, "example": "显示", "frequency": 806, "confusingChars": {"easy": ["日", "业"], "medium": ["业", "湿"], "hard": ["湿", "晃"]}}, "h_807": {"id": "h_807", "char": "湿", "pinyin": "shī", "level": 3, "stroke": 12, "example": "潮湿", "frequency": 807, "confusingChars": {"easy": ["水", "业"], "medium": ["显", "温"], "hard": ["温", "施"]}}, "h_808": {"id": "h_808", "char": "晒", "pinyin": "shài", "level": 3, "stroke": 10, "example": "晒太阳", "frequency": 808, "confusingChars": {"easy": ["日", "西"], "medium": ["洒", "西"], "hard": ["洒", "栖"]}}, "h_809": {"id": "h_809", "char": "穷", "pinyin": "qióng", "level": 3, "stroke": 7, "example": "贫穷", "frequency": 809, "confusingChars": {"easy": ["穴", "力"], "medium": ["空", "究"], "hard": ["究", "穹"]}}, "h_810": {"id": "h_810", "char": "究", "pinyin": "jiū", "level": 3, "stroke": 7, "example": "研究", "frequency": 810, "confusingChars": {"easy": ["穴", "九"], "medium": ["空", "穷"], "hard": ["穷", "九"]}}, "h_811": {"id": "h_811", "char": "积", "pinyin": "jī", "level": 3, "stroke": 10, "example": "积极", "frequency": 811, "confusingChars": {"easy": ["禾", "只"], "medium": ["和", "识"], "hard": ["绩", "辑"]}}, "h_812": {"id": "h_812", "char": "密", "pinyin": "mì", "level": 3, "stroke": 11, "example": "秘密", "frequency": 812, "confusingChars": {"easy": ["宀", "必"], "medium": ["蜜", "必"], "hard": ["蜜", "秘"]}}, "h_813": {"id": "h_813", "char": "斑", "pinyin": "bān", "level": 3, "stroke": 12, "example": "斑马", "frequency": 813, "confusingChars": {"easy": ["王", "文"], "medium": ["班", "玩"], "hard": ["班", "颁"]}}, "h_814": {"id": "h_814", "char": "趴", "pinyin": "pā", "level": 3, "stroke": 5, "example": "趴下", "frequency": 814, "confusingChars": {"easy": ["足", "八"], "medium": ["扒", "八"], "hard": ["扒", "吧"]}}, "h_815": {"id": "h_815", "char": "傻", "pinyin": "shǎ", "level": 3, "stroke": 13, "example": "傻瓜", "frequency": 815, "confusingChars": {"easy": ["人", "夕"], "medium": ["像", "俊"], "hard": ["沙", "俊"]}}, "h_816": {"id": "h_816", "char": "堡", "pinyin": "bǎo", "level": 3, "stroke": 12, "example": "城堡", "frequency": 816, "confusingChars": {"easy": ["保", "土"], "medium": ["保", "呆"], "hard": ["保", "宝"]}}, "h_817": {"id": "h_817", "char": "筑", "pinyin": "zhù", "level": 3, "stroke": 12, "example": "建筑", "frequency": 817, "confusingChars": {"easy": ["竹", "工"], "medium": ["恐", "巩"], "hard": ["竹", "恐"]}}, "h_818": {"id": "h_818", "char": "插", "pinyin": "chā", "level": 3, "stroke": 12, "example": "插入", "frequency": 818, "confusingChars": {"easy": ["手", "千"], "medium": ["播", "搜"], "hard": ["叉", "差"]}}, "h_819": {"id": "h_819", "char": "凶", "pinyin": "xiōng", "level": 3, "stroke": 4, "example": "凶猛", "frequency": 819, "confusingChars": {"easy": ["乂", "凵"], "medium": ["区", "风"], "hard": ["胸", "汹"]}}, "h_820": {"id": "h_820", "char": "狠", "pinyin": "hěn", "level": 3, "stroke": 9, "example": "凶狠", "frequency": 820, "confusingChars": {"easy": ["犭", "艮"], "medium": ["狼", "很"], "hard": ["很", "恨"]}}, "h_821": {"id": "h_821", "char": "充", "pinyin": "chōng", "level": 3, "stroke": 6, "example": "充分", "frequency": 821, "confusingChars": {"easy": ["亠", "儿"], "medium": ["允", "统"], "hard": ["冲", "允"]}}, "h_822": {"id": "h_822", "char": "药", "pinyin": "yào", "level": 3, "stroke": 9, "example": "吃药", "frequency": 822, "confusingChars": {"easy": ["草", "约"], "medium": ["约", "莉"], "hard": ["要", "约"]}}, "h_823": {"id": "h_823", "char": "厕", "pinyin": "cè", "level": 3, "stroke": 8, "example": "厕所", "frequency": 823, "confusingChars": {"easy": ["厂", "贝"], "medium": ["侧", "测"], "hard": ["侧", "测"]}}, "h_824": {"id": "h_824", "char": "所", "pinyin": "suǒ", "level": 2, "stroke": 8, "example": "所以", "frequency": 824, "confusingChars": {"easy": ["户", "斤"], "medium": ["听", "近"], "hard": ["索", "锁"]}}, "h_825": {"id": "h_825", "char": "馆", "pinyin": "guǎn", "level": 3, "stroke": 11, "example": "图书馆", "frequency": 825, "confusingChars": {"easy": ["食", "官"], "medium": ["管", "官"], "hard": ["管", "官"]}}, "h_826": {"id": "h_826", "char": "览", "pinyin": "lǎn", "level": 3, "stroke": 9, "example": "展览", "frequency": 826, "confusingChars": {"easy": ["见", "〢"], "medium": ["觉", "监"], "hard": ["揽", "缆"]}}, "h_827": {"id": "h_827", "char": "胜", "pinyin": "shèng", "level": 3, "stroke": 9, "example": "胜利", "frequency": 827, "confusingChars": {"easy": ["月", "生"], "medium": ["生", "姓"], "hard": ["牲", "盛"]}}, "h_828": {"id": "h_828", "char": "央", "pinyin": "yāng", "level": 3, "stroke": 5, "example": "中央", "frequency": 828, "confusingChars": {"easy": ["大", "中"], "medium": ["英", "秧"], "hard": ["英", "秧"]}}, "h_829": {"id": "h_829", "char": "秀", "pinyin": "xiù", "level": 3, "stroke": 7, "example": "秀丽", "frequency": 829, "confusingChars": {"easy": ["禾", "乃"], "medium": ["季", "李"], "hard": ["季", "透"]}}, "h_830": {"id": "h_830", "char": "著", "pinyin": "zhù", "level": 3, "stroke": 11, "example": "著名", "frequency": 830, "confusingChars": {"easy": ["草", "者"], "medium": ["者", "暑"], "hard": ["住", "助"]}}, "h_831": {"id": "h_831", "char": "闪", "pinyin": "shǎn", "level": 3, "stroke": 5, "example": "闪光", "frequency": 831, "confusingChars": {"easy": ["门", "人"], "medium": ["门", "问"], "hard": ["陕", "扇"]}}, "h_832": {"id": "h_832", "char": "躲", "pinyin": "duǒ", "level": 3, "stroke": 13, "example": "躲开", "frequency": 832, "confusingChars": {"easy": ["身", "朵"], "medium": ["朵", "射"], "hard": ["垛", "舵"]}}, "h_833": {"id": "h_833", "char": "枯", "pinyin": "kū", "level": 3, "stroke": 9, "example": "枯草", "frequency": 833, "confusingChars": {"easy": ["木", "古"], "medium": ["苦", "古"], "hard": ["苦", "哭"]}}, "h_834": {"id": "h_834", "char": "宿", "pinyin": "sù", "level": 3, "stroke": 11, "example": "宿舍", "frequency": 834, "confusingChars": {"easy": ["宀", "百"], "medium": ["缩", "佰"], "hard": ["缩", "素"]}}, "h_835": {"id": "h_835", "char": "徐", "pinyin": "xú", "level": 3, "stroke": 10, "example": "徐徐", "frequency": 835, "confusingChars": {"easy": ["彳", "余"], "medium": ["除", "余"], "hard": ["除", "叙"]}}, "h_836": {"id": "h_836", "char": "店", "pinyin": "diàn", "level": 2, "stroke": 8, "example": "书店", "frequency": 836, "confusingChars": {"easy": ["广", "占"], "medium": ["站", "占"], "hard": ["站", "垫"]}}, "h_837": {"id": "h_837", "char": "荣", "pinyin": "róng", "level": 3, "stroke": 9, "example": "光荣", "frequency": 837, "confusingChars": {"easy": ["草", "木"], "medium": ["茶", "劳"], "hard": ["容", "融"]}}, "h_838": {"id": "h_838", "char": "烧", "pinyin": "shāo", "level": 3, "stroke": 10, "example": "发烧", "frequency": 838, "confusingChars": {"easy": ["火", "尧"], "medium": ["浇", "晓"], "hard": ["少", "哨"]}}, "h_839": {"id": "h_839", "char": "笋", "pinyin": "sǔn", "level": 3, "stroke": 10, "example": "竹笋", "frequency": 839, "confusingChars": {"easy": ["竹", "尹"], "medium": ["伊", "尹"], "hard": ["孙", "损"]}}, "h_840": {"id": "h_840", "char": "芽", "pinyin": "yá", "level": 3, "stroke": 7, "example": "发芽", "frequency": 840, "confusingChars": {"easy": ["草", "牙"], "medium": ["牙", "讶"], "hard": ["呀", "牙"]}}, "h_841": {"id": "h_841", "char": "喊", "pinyin": "hǎn", "level": 3, "stroke": 12, "example": "喊叫", "frequency": 841, "confusingChars": {"easy": ["口", "成"], "medium": ["减", "咸"], "hard": ["感", "撼"]}}, "h_842": {"id": "h_842", "char": "呼", "pinyin": "hū", "level": 3, "stroke": 8, "example": "呼吸", "frequency": 842, "confusingChars": {"easy": ["口", "乎"], "medium": ["乎", "平"], "hard": ["乎", "乎"]}}, "h_843": {"id": "h_843", "char": "唤", "pinyin": "huàn", "level": 3, "stroke": 10, "example": "呼唤", "frequency": 843, "confusingChars": {"easy": ["口", "央"], "medium": ["换", "焕"], "hard": ["换", "幻"]}}, "h_844": {"id": "h_844", "char": "兄", "pinyin": "xiōng", "level": 3, "stroke": 5, "example": "兄弟", "frequency": 844, "confusingChars": {"easy": ["口", "儿"], "medium": ["儿", "只"], "hard": ["凶", "胸"]}}, "h_845": {"id": "h_845", "char": "呆", "pinyin": "dāi", "level": 3, "stroke": 7, "example": "发呆", "frequency": 845, "confusingChars": {"easy": ["口", "木"], "medium": ["果", "杏"], "hard": ["待", "保"]}}, "h_846": {"id": "h_846", "char": "撒", "pinyin": "sā", "level": 3, "stroke": 15, "example": "撒手", "frequency": 846, "confusingChars": {"easy": ["手", "散"], "medium": ["散", "撤"], "hard": ["洒", "散"]}}, "h_847": {"id": "h_847", "char": "谎", "pinyin": "huǎng", "level": 3, "stroke": 14, "example": "说谎", "frequency": 847, "confusingChars": {"easy": ["言", "荒"], "medium": ["慌", "荒"], "hard": ["晃", "恍"]}}, "h_848": {"id": "h_848", "char": "幼", "pinyin": "yòu", "level": 3, "stroke": 5, "example": "幼儿", "frequency": 848, "confusingChars": {"easy": ["幺", "力"], "medium": ["幻", "力"], "hard": ["幻", "右"]}}, "h_849": {"id": "h_849", "char": "挑", "pinyin": "tiāo", "level": 3, "stroke": 9, "example": "挑选", "frequency": 849, "confusingChars": {"easy": ["手", "兆"], "medium": ["桃", "跳"], "hard": ["眺", "逃"]}}, "h_850": {"id": "h_850", "char": "秧", "pinyin": "yāng", "level": 3, "stroke": 10, "example": "秧苗", "frequency": 850, "confusingChars": {"easy": ["禾", "央"], "medium": ["央", "英"], "hard": ["殃", "央"]}}, "h_851": {"id": "h_851", "char": "披", "pinyin": "pī", "level": 3, "stroke": 8, "example": "披风", "frequency": 851, "confusingChars": {"easy": ["手", "皮"], "medium": ["被", "皮"], "hard": ["波", "坡"]}}, "h_852": {"id": "h_852", "char": "鼓", "pinyin": "gǔ", "level": 3, "stroke": 13, "example": "打鼓", "frequency": 852, "confusingChars": {"easy": ["支", "豆"], "medium": ["彭", "喜"], "hard": ["古", "股"]}}, "h_853": {"id": "h_853", "char": "疼", "pinyin": "téng", "level": 3, "stroke": 10, "example": "疼痛", "frequency": 853, "confusingChars": {"easy": ["疒", "冬"], "medium": ["病", "冬"], "hard": ["痛", "通"]}}, "h_854": {"id": "h_854", "char": "遇", "pinyin": "yù", "level": 3, "stroke": 12, "example": "遇到", "frequency": 854, "confusingChars": {"easy": ["走", "禺"], "medium": ["偶", "愚"], "hard": ["御", "寓"]}}, "h_855": {"id": "h_855", "char": "匹", "pinyin": "pǐ", "level": 3, "stroke": 4, "example": "马匹", "frequency": 855, "confusingChars": {"easy": ["儿", "四"], "medium": ["四", "医"], "hard": ["区", "巨"]}}, "h_856": {"id": "h_856", "char": "袋", "pinyin": "dài", "level": 3, "stroke": 11, "example": "口袋", "frequency": 856, "confusingChars": {"easy": ["代", "衣"], "medium": ["代", "衣"], "hard": ["贷", "货"]}}, "h_857": {"id": "h_857", "char": "窜", "pinyin": "cuàn", "level": 3, "stroke": 18, "example": "逃窜", "frequency": 857, "confusingChars": {"easy": ["穴", "串"], "medium": ["串", "鼠"], "hard": ["串", "窜"]}}, "h_858": {"id": "h_858", "char": "漂", "pinyin": "piào", "level": 3, "stroke": 14, "example": "漂亮", "frequency": 858, "confusingChars": {"easy": ["水", "票"], "medium": ["飘", "票"], "hard": ["飘", "瓢"]}}, "h_859": {"id": "h_859", "char": "飘", "pinyin": "piāo", "level": 3, "stroke": 15, "example": "飘扬", "frequency": 859, "confusingChars": {"easy": ["风", "票"], "medium": ["漂", "票"], "hard": ["漂", "瓢"]}}, "h_860": {"id": "h_860", "char": "幸", "pinyin": "xìng", "level": 3, "stroke": 8, "example": "幸福", "frequency": 860, "confusingChars": {"easy": ["土", "羊"], "medium": ["辛", "土"], "hard": ["辛", "兴"]}}, "h_861": {"id": "h_861", "char": "福", "pinyin": "fú", "level": 3, "stroke": 13, "example": "幸福", "frequency": 861, "confusingChars": {"easy": ["示", "田"], "medium": ["幅", "富"], "hard": ["福", "服"]}}, "h_862": {"id": "h_862", "char": "句", "pinyin": "jù", "level": 2, "stroke": 5, "example": "句子", "frequency": 862, "confusingChars": {"easy": ["口", "勹"], "medium": ["包", "勾"], "hard": ["局", "旬"]}}, "h_863": {"id": "h_863", "char": "逗", "pinyin": "dòu", "level": 3, "stroke": 10, "example": "逗笑", "frequency": 863, "confusingChars": {"easy": ["豆", "走"], "medium": ["豆", "痘"], "hard": ["读", "斗"]}}, "h_864": {"id": "h_864", "char": "狂", "pinyin": "kuáng", "level": 3, "stroke": 7, "example": "疯狂", "frequency": 864, "confusingChars": {"easy": ["犭", "王"], "medium": ["汪", "往"], "hard": ["逛", "况"]}}, "h_865": {"id": "h_865", "char": "吼", "pinyin": "hǒu", "level": 3, "stroke": 7, "example": "吼叫", "frequency": 865, "confusingChars": {"easy": ["口", "孔"], "medium": ["孔", "口"], "hard": ["孔", "乱"]}}, "h_866": {"id": "h_866", "char": "威", "pinyin": "wēi", "level": 3, "stroke": 9, "example": "威风", "frequency": 866, "confusingChars": {"easy": ["女", "戈"], "medium": ["咸", "成"], "hard": ["危", "微"]}}, "h_867": {"id": "h_867", "char": "武", "pinyin": "wǔ", "level": 3, "stroke": 8, "example": "武术", "frequency": 867, "confusingChars": {"easy": ["一", "止"], "medium": ["式", "斌"], "hard": ["五", "舞"]}}, "h_868": {"id": "h_868", "char": "爪", "pinyin": "zhuǎ", "level": 3, "stroke": 4, "example": "爪子", "frequency": 868, "confusingChars": {"easy": ["丿", "八"], "medium": ["瓜", "抓"], "hard": ["抓", "爬"]}}, "h_869": {"id": "h_869", "char": "胆", "pinyin": "dǎn", "level": 3, "stroke": 9, "example": "大胆", "frequency": 869, "confusingChars": {"easy": ["月", "旦"], "medium": ["但", "旦"], "hard": ["担", "但是"]}}, "h_870": {"id": "h_870", "char": "鬼", "pinyin": "guǐ", "level": 3, "stroke": 9, "example": "鬼怪", "frequency": 870, "confusingChars": {"easy": ["白", "儿"], "medium": ["龟", "电"], "hard": ["龟", "愧"]}}, "h_871": {"id": "h_871", "char": "刮", "pinyin": "guā", "level": 3, "stroke": 8, "example": "刮风", "frequency": 871, "confusingChars": {"easy": ["舌", "刀"], "medium": ["乱", "敌"], "hard": ["适", "括"]}}, "h_872": {"id": "h_872", "char": "忍", "pinyin": "rěn", "level": 3, "stroke": 7, "example": "忍耐", "frequency": 872, "confusingChars": {"easy": ["刃", "心"], "medium": ["刃", "心"], "hard": ["认", "任"]}}, "h_873": {"id": "h_873", "char": "绑", "pinyin": "bǎng", "level": 3, "stroke": 9, "example": "绑住", "frequency": 873, "confusingChars": {"easy": ["丝", "邦"], "medium": ["帮", "邦"], "hard": ["帮", "梆"]}}, "h_874": {"id": "h_874", "char": "抽", "pinyin": "chōu", "level": 3, "stroke": 8, "example": "抽出", "frequency": 874, "confusingChars": {"easy": ["手", "由"], "medium": ["油", "袖"], "hard": ["轴", "宙"]}}, "h_875": {"id": "h_875", "char": "续", "pinyin": "xù", "level": 3, "stroke": 11, "example": "继续", "frequency": 875, "confusingChars": {"easy": ["丝", "卖"], "medium": ["读", "卖"], "hard": ["读", "赎"]}}, "h_876": {"id": "h_876", "char": "筝", "pinyin": "zhēng", "level": 3, "stroke": 12, "example": "风筝", "frequency": 876, "confusingChars": {"easy": ["竹", "争"], "medium": ["争", "净"], "hard": ["挣", "睁"]}}, "h_877": {"id": "h_877", "char": "眨", "pinyin": "zhǎ", "level": 3, "stroke": 9, "example": "眨眼", "frequency": 877, "confusingChars": {"easy": ["目", "乏"], "medium": ["泛", "乏"], "hard": ["泛", "贬"]}}, "h_878": {"id": "h_878", "char": "盯", "pinyin": "dīng", "level": 3, "stroke": 7, "example": "盯着", "frequency": 878, "confusingChars": {"easy": ["目", "丁"], "medium": ["钉", "订"], "hard": ["顶", "叮"]}}, "h_879": {"id": "h_879", "char": "扶", "pinyin": "fú", "level": 3, "stroke": 7, "example": "扶手", "frequency": 879, "confusingChars": {"easy": ["手", "夫"], "medium": ["夫", "肤"], "hard": ["抚", "肤"]}}, "h_880": {"id": "h_880", "char": "哨", "pinyin": "shào", "level": 3, "stroke": 10, "example": "口哨", "frequency": 880, "confusingChars": {"easy": ["口", "肖"], "medium": ["梢", "消"], "hard": ["俏", "峭"]}}, "h_881": {"id": "h_881", "char": "偷", "pinyin": "tōu", "level": 3, "stroke": 11, "example": "小偷", "frequency": 881, "confusingChars": {"easy": ["人", "俞"], "medium": ["愉", "输"], "hard": ["输", "愈"]}}, "h_882": {"id": "h_882", "char": "嚷", "pinyin": "rǎng", "level": 3, "stroke": 20, "example": "叫嚷", "frequency": 882, "confusingChars": {"easy": ["口", "襄"], "medium": ["镶", "壤"], "hard": ["壤", "攘"]}}, "h_883": {"id": "h_883", "char": "强", "pinyin": "qiáng", "level": 3, "stroke": 12, "example": "强大", "frequency": 883, "confusingChars": {"easy": ["弓", "虫"], "medium": ["疆", "弘"], "hard": ["墙", "蔷"]}}, "h_884": {"id": "h_884", "char": "弱", "pinyin": "ruò", "level": 3, "stroke": 10, "example": "弱小", "frequency": 884, "confusingChars": {"easy": ["弓", "冫"], "medium": ["溺", "羽"], "hard": ["溺", "若"]}}, "h_885": {"id": "h_885", "char": "栽", "pinyin": "zāi", "level": 3, "stroke": 10, "example": "栽树", "frequency": 885, "confusingChars": {"easy": ["木", "戈"], "medium": ["裁", "载"], "hard": ["载", "裁"]}}, "h_886": {"id": "h_886", "char": "檐", "pinyin": "yán", "level": 3, "stroke": 17, "example": "房檐", "frequency": 886, "confusingChars": {"easy": ["木", "言"], "medium": ["瞻", "詹"], "hard": ["瞻", "赡"]}}, "h_887": {"id": "h_887", "char": "温", "pinyin": "wēn", "level": 2, "stroke": 12, "example": "温暖", "frequency": 887, "confusingChars": {"easy": ["水", "日"], "medium": ["湿", "皿"], "hard": ["湿", "瘟"]}}, "h_888": {"id": "h_888", "char": "暴", "pinyin": "bào", "level": 3, "stroke": 15, "example": "暴雨", "frequency": 888, "confusingChars": {"easy": ["日", "水"], "medium": ["爆", "瀑"], "hard": ["爆", "曝"]}}, "h_889": {"id": "h_889", "char": "晾", "pinyin": "liàng", "level": 3, "stroke": 12, "example": "晾晒", "frequency": 889, "confusingChars": {"easy": ["日", "京"], "medium": ["凉", "景"], "hard": ["凉", "谅"]}}, "h_890": {"id": "h_890", "char": "顾", "pinyin": "gù", "level": 3, "stroke": 10, "example": "照顾", "frequency": 890, "confusingChars": {"easy": ["页", "厄"], "medium": ["愿", "烦"], "hard": ["故", "固"]}}, "h_891": {"id": "h_891", "char": "祝", "pinyin": "zhù", "level": 2, "stroke": 9, "example": "庆祝", "frequency": 891, "confusingChars": {"easy": ["示", "兄"], "medium": ["视", "况"], "hard": ["注", "住"]}}, "h_892": {"id": "h_892", "char": "贺", "pinyin": "hè", "level": 3, "stroke": 9, "example": "祝贺", "frequency": 892, "confusingChars": {"easy": ["加", "贝"], "medium": ["驾", "架"], "hard": ["鹤", "赫"]}}, "h_893": {"id": "h_893", "char": "盼", "pinyin": "pàn", "level": 3, "stroke": 9, "example": "盼望", "frequency": 893, "confusingChars": {"easy": ["目", "分"], "medium": ["分", "扮"], "hard": ["判", "叛"]}}, "h_894": {"id": "h_894", "char": "扬", "pinyin": "yáng", "level": 3, "stroke": 6, "example": "表扬", "frequency": 894, "confusingChars": {"easy": ["手", "昜"], "medium": ["杨", "汤"], "hard": ["杨", "场"]}}, "h_895": {"id": "h_895", "char": "餐", "pinyin": "cān", "level": 3, "stroke": 16, "example": "早餐", "frequency": 895, "confusingChars": {"easy": ["食", "又"], "medium": ["食", "参"], "hard": ["参", "餐"]}}, "h_896": {"id": "h_896", "char": "饮", "pinyin": "yǐn", "level": 3, "stroke": 7, "example": "饮料", "frequency": 896, "confusingChars": {"easy": ["食", "欠"], "medium": ["软", "吹"], "hard": ["引", "隐"]}}, "h_897": {"id": "h_897", "char": "馒", "pinyin": "mán", "level": 3, "stroke": 14, "example": "馒头", "frequency": 897, "confusingChars": {"easy": ["食", "日"], "medium": ["漫", "慢"], "hard": ["漫", "慢"]}}, "h_898": {"id": "h_898", "char": "馋", "pinyin": "chán", "level": 3, "stroke": 12, "example": "嘴馋", "frequency": 898, "confusingChars": {"easy": ["食", "免"], "medium": ["搀", "免"], "hard": ["缠", "谗"]}}, "h_899": {"id": "h_899", "char": "验", "pinyin": "yàn", "level": 3, "stroke": 10, "example": "考验", "frequency": 899, "confusingChars": {"easy": ["马", "佥"], "medium": ["脸", "检"], "hard": ["验", "检"]}}, "h_900": {"id": "h_900", "char": "演", "pinyin": "yǎn", "level": 3, "stroke": 14, "example": "表演", "frequency": 900, "confusingChars": {"easy": ["水", "寅"], "medium": ["寅", "黄"], "hard": ["眼", "掩"]}}, "h_901": {"id": "h_901", "char": "奏", "pinyin": "zòu", "level": 3, "stroke": 9, "example": "演奏", "frequency": 901, "confusingChars": {"easy": ["天", "夫"], "medium": ["凑", "春"], "hard": ["凑", "揍"]}}, "h_902": {"id": "h_902", "char": "瞧", "pinyin": "qiáo", "level": 3, "stroke": 17, "example": "瞧见", "frequency": 902, "confusingChars": {"easy": ["目", "焦"], "medium": ["焦", "樵"], "hard": ["焦", "桥"]}}, "h_903": {"id": "h_903", "char": "懂", "pinyin": "dǒng", "level": 3, "stroke": 15, "example": "听懂", "frequency": 903, "confusingChars": {"easy": ["心", "重"], "medium": ["董", "重"], "hard": ["动", "冻"]}}, "h_904": {"id": "h_904", "char": "貌", "pinyin": "mào", "level": 3, "stroke": 14, "example": "礼貌", "frequency": 904, "confusingChars": {"easy": ["豸", "白"], "medium": ["豹", "藐"], "hard": ["帽", "茂"]}}, "h_905": {"id": "h_905", "char": "礼", "pinyin": "lǐ", "level": 2, "stroke": 5, "example": "礼物", "frequency": 905, "confusingChars": {"easy": ["示", "乚"], "medium": ["扎", "乱"], "hard": ["理", "里"]}}, "h_906": {"id": "h_906", "char": "敬", "pinyin": "jìng", "level": 3, "stroke": 12, "example": "敬礼", "frequency": 906, "confusingChars": {"easy": ["苟", "文"], "medium": ["警", "苟"], "hard": ["静", "竟"]}}, "h_907": {"id": "h_907", "char": "尊", "pinyin": "zūn", "level": 3, "stroke": 12, "example": "尊敬", "frequency": 907, "confusingChars": {"easy": ["酋", "寸"], "medium": ["遵", "奠"], "hard": ["遵", "遵"]}}, "h_908": {"id": "h_908", "char": "复", "pinyin": "fù", "level": 3, "stroke": 9, "example": "复习", "frequency": 908, "confusingChars": {"easy": ["夂", "日"], "medium": ["夏", "腹"], "hard": ["副", "富"]}}, "h_909": {"id": "h_909", "char": "杂", "pinyin": "zá", "level": 3, "stroke": 6, "example": "复杂", "frequency": 909, "confusingChars": {"easy": ["九", "木"], "medium": ["朵", "杀"], "hard": ["砸", "咱"]}}, "h_910": {"id": "h_910", "char": "闲", "pinyin": "xián", "level": 3, "stroke": 7, "example": "休闲", "frequency": 910, "confusingChars": {"easy": ["门", "木"], "medium": ["困", "闭"], "hard": ["贤", "咸"]}}, "h_911": {"id": "h_911", "char": "易", "pinyin": "yì", "level": 3, "stroke": 8, "example": "容易", "frequency": 911, "confusingChars": {"easy": ["日", "勿"], "medium": ["惕", "剔"], "hard": ["意", "义"]}}, "h_912": {"id": "h_912", "char": "简", "pinyin": "jiǎn", "level": 3, "stroke": 13, "example": "简单", "frequency": 912, "confusingChars": {"easy": ["竹", "间"], "medium": ["间", "竹"], "hard": ["减", "检"]}}, "h_913": {"id": "h_913", "char": "单", "pinyin": "dān", "level": 2, "stroke": 8, "example": "简单", "frequency": 913, "confusingChars": {"easy": ["甲", "早"], "medium": ["甲", "早"], "hard": ["担", "弹"]}}, "h_914": {"id": "h_914", "char": "鹅", "pinyin": "é", "level": 3, "stroke": 12, "example": "天鹅", "frequency": 914, "confusingChars": {"easy": ["鸟", "我"], "medium": ["鸭", "我"], "hard": ["饿", "俄"]}}, "h_915": {"id": "h_915", "char": "虾", "pinyin": "xiā", "level": 3, "stroke": 9, "example": "鱼虾", "frequency": 915, "confusingChars": {"easy": ["虫", "下"], "medium": ["下", "吓"], "hard": ["吓", "瞎"]}}, "h_916": {"id": "h_916", "char": "壳", "pinyin": "ké", "level": 3, "stroke": 7, "example": "贝壳", "frequency": 916, "confusingChars": {"easy": ["士", "几"], "medium": ["亮", "秃"], "hard": ["壶", "克"]}}, "h_917": {"id": "h_917", "char": "骨", "pinyin": "gǔ", "level": 3, "stroke": 9, "example": "骨头", "frequency": 917, "confusingChars": {"easy": ["月", "冂"], "medium": ["滑", "肯"], "hard": ["古", "谷"]}}, "h_918": {"id": "h_918", "char": "翅", "pinyin": "chì", "level": 3, "stroke": 10, "example": "翅膀", "frequency": 918, "confusingChars": {"easy": ["羽", "支"], "medium": ["翘", "支"], "hard": ["赤", "斥"]}}, "h_919": {"id": "h_919", "char": "膀", "pinyin": "bǎng", "level": 3, "stroke": 14, "example": "翅膀", "frequency": 919, "confusingChars": {"easy": ["月", "旁"], "medium": ["傍", "旁"], "hard": ["榜", "帮"]}}, "h_920": {"id": "h_920", "char": "臂", "pinyin": "bì", "level": 3, "stroke": 17, "example": "手臂", "frequency": 920, "confusingChars": {"easy": ["月", "辛"], "medium": ["壁", "劈"], "hard": ["壁", "必"]}}, "h_921": {"id": "h_921", "char": "腹", "pinyin": "fù", "level": 3, "stroke": 13, "example": "腹部", "frequency": 921, "confusingChars": {"easy": ["月", "复"], "medium": ["复", "履"], "hard": ["复", "富"]}}, "h_922": {"id": "h_922", "char": "膝", "pinyin": "xī", "level": 3, "stroke": 15, "example": "膝盖", "frequency": 922, "confusingChars": {"easy": ["月", "木"], "medium": ["漆", "膝"], "hard": ["吸", "西"]}}, "h_923": {"id": "h_923", "char": "迅", "pinyin": "xùn", "level": 3, "stroke": 6, "example": "迅速", "frequency": 923, "confusingChars": {"easy": ["辶", "十"], "medium": ["讯", "汛"], "hard": ["讯", "训"]}}, "h_924": {"id": "h_924", "char": "速", "pinyin": "sù", "level": 3, "stroke": 10, "example": "速度", "frequency": 924, "confusingChars": {"easy": ["辶", "束"], "medium": ["束", "悚"], "hard": ["素", "宿"]}}, "h_925": {"id": "h_925", "char": "奔", "pinyin": "bēn", "level": 3, "stroke": 8, "example": "奔跑", "frequency": 925, "confusingChars": {"easy": ["大", "十"], "medium": ["笨", "卉"], "hard": ["本", "苯"]}}, "h_926": {"id": "h_926", "char": "巧", "pinyin": "qiǎo", "level": 3, "stroke": 5, "example": "灵巧", "frequency": 926, "confusingChars": {"easy": ["工", "5"], "medium": ["功", "朽"], "hard": ["桥", "乔"]}}, "h_927": {"id": "h_927", "char": "妙", "pinyin": "miào", "level": 3, "stroke": 7, "example": "奇妙", "frequency": 927, "confusingChars": {"easy": ["女", "少"], "medium": ["少", "秒"], "hard": ["秒", "吵"]}}, "h_928": {"id": "h_928", "char": "异", "pinyin": "yì", "level": 3, "stroke": 6, "example": "异常", "frequency": 928, "confusingChars": {"easy": ["巳", "廾"], "medium": ["导", "昇"], "hard": ["意", "义"]}}, "h_929": {"id": "h_929", "char": "雾", "pinyin": "wù", "level": 3, "stroke": 13, "example": "大雾", "frequency": 929, "confusingChars": {"easy": ["雨", "务"], "medium": ["雪", "雷"], "hard": ["露", "霉"]}}, "h_930": {"id": "h_930", "char": "露", "pinyin": "lù", "level": 3, "stroke": 21, "example": "露水", "frequency": 930, "confusingChars": {"easy": ["雨", "路"], "medium": ["雾", "霜"], "hard": ["路", "潞"]}}, "h_931": {"id": "h_931", "char": "震", "pinyin": "zhèn", "level": 3, "stroke": 15, "example": "地震", "frequency": 931, "confusingChars": {"easy": ["雨", "辰"], "medium": ["需", "晨"], "hard": ["振", "赈"]}}, "h_932": {"id": "h_932", "char": "埋", "pinyin": "mái", "level": 3, "stroke": 10, "example": "埋没", "frequency": 932, "confusingChars": {"easy": ["土", "里"], "medium": ["理", "里"], "hard": ["理", "狸"]}}, "h_933": {"id": "h_933", "char": "藏", "pinyin": "cáng", "level": 3, "stroke": 17, "example": "躲藏", "frequency": 933, "confusingChars": {"easy": ["草", "脏"], "medium": ["脏", "茂"], "hard": ["臧", "脏"]}}, "h_934": {"id": "h_934", "char": "烦", "pinyin": "fán", "level": 3, "stroke": 10, "example": "烦恼", "frequency": 934, "confusingChars": {"easy": ["火", "页"], "medium": ["顶", "须"], "hard": ["繁", "频"]}}, "h_935": {"id": "h_935", "char": "恼", "pinyin": "nǎo", "level": 3, "stroke": 9, "example": "烦恼", "frequency": 935, "confusingChars": {"easy": ["心", "凶"], "medium": ["脑", "离"], "hard": ["脑", "瑙"]}}, "h_936": {"id": "h_936", "char": "怒", "pinyin": "nù", "level": 3, "stroke": 9, "example": "发怒", "frequency": 936, "confusingChars": {"easy": ["奴", "心"], "medium": ["努", "恕"], "hard": ["努", "弩"]}}, "h_937": {"id": "h_937", "char": "愁", "pinyin": "chóu", "level": 3, "stroke": 13, "example": "发愁", "frequency": 937, "confusingChars": {"easy": ["秋", "心"], "medium": ["想", "忽"], "hard": ["秋", "揪"]}}, "h_938": {"id": "h_938", "char": "怨", "pinyin": "yuàn", "level": 3, "stroke": 9, "example": "埋怨", "frequency": 938, "confusingChars": {"easy": ["夕", "心"], "medium": ["怒", "危"], "hard": ["苑", "鸳"]}}, "h_939": {"id": "h_939", "char": "银", "pinyin": "yín", "level": 3, "stroke": 11, "example": "银行", "frequency": 939, "confusingChars": {"easy": ["金", "良"], "medium": ["跟", "根"], "hard": ["很", "狠"]}}, "h_940": {"id": "h_940", "char": "珍", "pinyin": "zhēn", "level": 3, "stroke": 9, "example": "珍惜", "frequency": 940, "confusingChars": {"easy": ["王", "人"], "medium": ["诊", "趁"], "hard": ["真", "贞"]}}, "h_941": {"id": "h_941", "char": "惜", "pinyin": "xī", "level": 3, "stroke": 11, "example": "可惜", "frequency": 941, "confusingChars": {"easy": ["心", "昔"], "medium": ["借", "错"], "hard": ["昔", "腊"]}}, "h_942": {"id": "h_942", "char": "艺", "pinyin": "yì", "level": 3, "stroke": 4, "example": "艺术", "frequency": 942, "confusingChars": {"easy": ["乙", "艹"], "medium": ["芝", "乞"], "hard": ["忆", "亿"]}}, "h_943": {"id": "h_943", "char": "艰", "pinyin": "jiān", "level": 4, "stroke": 8, "example": "艰苦", "frequency": 943, "confusingChars": {"easy": ["艮", "又"], "medium": ["跟", "限"], "hard": ["坚", "间"]}}, "h_944": {"id": "h_944", "char": "勤", "pinyin": "qín", "level": 3, "stroke": 13, "example": "勤劳", "frequency": 944, "confusingChars": {"easy": ["力", "堇"], "medium": ["勒", "谨"], "hard": ["琴", "芹"]}}, "h_945": {"id": "h_945", "char": "职", "pinyin": "zhí", "level": 3, "stroke": 11, "example": "职业", "frequency": 945, "confusingChars": {"easy": ["耳", "只"], "medium": ["识", "积"], "hard": ["只", "织"]}}, "h_946": {"id": "h_946", "char": "官", "pinyin": "guān", "level": 3, "stroke": 8, "example": "做官", "frequency": 946, "confusingChars": {"easy": ["宀", "口"], "medium": ["宫", "管"], "hard": ["馆", "管"]}}, "h_947": {"id": "h_947", "char": "营", "pinyin": "yíng", "level": 3, "stroke": 11, "example": "露营", "frequency": 947, "confusingChars": {"easy": ["草", "宫"], "medium": ["管", "莹"], "hard": ["莹", "萤"]}}, "h_948": {"id": "h_948", "char": "踩", "pinyin": "cǎi", "level": 3, "stroke": 15, "example": "踩踏", "frequency": 948, "confusingChars": {"easy": ["足", "采"], "medium": ["彩", "菜"], "hard": ["采", "彩"]}}, "h_949": {"id": "h_949", "char": "踏", "pinyin": "tà", "level": 3, "stroke": 15, "example": "踏步", "frequency": 949, "confusingChars": {"easy": ["足", "水"], "medium": ["踢", "路"], "hard": ["塌", "沓"]}}, "h_950": {"id": "h_950", "char": "蹲", "pinyin": "dūn", "level": 3, "stroke": 19, "example": "蹲下", "frequency": 950, "confusingChars": {"easy": ["足", "尊"], "medium": ["尊", "遵"], "hard": ["遵", "尊"]}}, "h_951": {"id": "h_951", "char": "捧", "pinyin": "pěng", "level": 3, "stroke": 11, "example": "捧着", "frequency": 951, "confusingChars": {"easy": ["手", "奉"], "medium": ["棒", "俸"], "hard": ["碰", "棒"]}}, "h_952": {"id": "h_952", "char": "掏", "pinyin": "tāo", "level": 3, "stroke": 11, "example": "掏出", "frequency": 952, "confusingChars": {"easy": ["手", "缶"], "medium": ["陶", "淘"], "hard": ["淘", "陶"]}}, "h_953": {"id": "h_953", "char": "投", "pinyin": "tóu", "level": 3, "stroke": 7, "example": "投入", "frequency": 953, "confusingChars": {"easy": ["手", "几"], "medium": ["没", "设"], "hard": ["头", "透"]}}, "h_954": {"id": "h_954", "char": "傲", "pinyin": "ào", "level": 3, "stroke": 12, "example": "骄傲", "frequency": 954, "confusingChars": {"easy": ["人", "放"], "medium": ["激", "敖"], "hard": ["遨", "熬"]}}, "h_955": {"id": "h_955", "char": "谦", "pinyin": "qiān", "level": 4, "stroke": 12, "example": "谦虚", "frequency": 955, "confusingChars": {"easy": ["言", "兼"], "medium": ["歉", "廉"], "hard": ["牵", "铅"]}}, "h_956": {"id": "h_956", "char": "虚", "pinyin": "xū", "level": 3, "stroke": 11, "example": "谦虚", "frequency": 956, "confusingChars": {"easy": ["业", "虎"], "medium": ["虎", "虑"], "hard": ["需", "须"]}}, "h_957": {"id": "h_957", "char": "镜", "pinyin": "jìng", "level": 3, "stroke": 16, "example": "镜子", "frequency": 957, "confusingChars": {"easy": ["金", "竟"], "medium": ["境", "钟"], "hard": ["境", "竟"]}}, "h_958": {"id": "h_958", "char": "盒", "pinyin": "hé", "level": 3, "stroke": 11, "example": "盒子", "frequency": 958, "confusingChars": {"easy": ["合", "皿"], "medium": ["盆", "盘"], "hard": ["合", "河"]}}, "h_959": {"id": "h_959", "char": "罐", "pinyin": "guàn", "level": 3, "stroke": 23, "example": "罐头", "frequency": 959, "confusingChars": {"easy": ["缶", "雚"], "medium": ["灌", "缸"], "hard": ["灌", "鹳"]}}, "h_960": {"id": "h_960", "char": "脆", "pinyin": "cuì", "level": 3, "stroke": 10, "example": "清脆", "frequency": 960, "confusingChars": {"easy": ["月", "危"], "medium": ["跪", "桅"], "hard": ["翠", "粹"]}}, "h_961": {"id": "h_961", "char": "窄", "pinyin": "zhǎi", "level": 3, "stroke": 10, "example": "窄小", "frequency": 961, "confusingChars": {"easy": ["穴", "作"], "medium": ["作", "昨"], "hard": ["摘", "债"]}}, "h_962": {"id": "h_962", "char": "坚", "pinyin": "jiān", "level": 3, "stroke": 7, "example": "坚持", "frequency": 962, "confusingChars": {"easy": ["土", "臣"], "medium": ["竖", "贤"], "hard": ["间", "肩"]}}, "h_963": {"id": "h_963", "char": "固", "pinyin": "gù", "level": 3, "stroke": 8, "example": "固定", "frequency": 963, "confusingChars": {"easy": ["口", "古"], "medium": ["因", "困"], "hard": ["故", "顾"]}}, "h_964": {"id": "h_964", "char": "绩", "pinyin": "jì", "level": 3, "stroke": 11, "example": "成绩", "frequency": 964, "confusingChars": {"easy": ["丝", "责"], "medium": ["责", "积"], "hard": ["纪", "迹"]}}, "h_965": {"id": "h_965", "char": "效", "pinyin": "xiào", "level": 3, "stroke": 10, "example": "效果", "frequency": 965, "confusingChars": {"easy": ["交", "攵"], "medium": ["郊", "校"], "hard": ["笑", "校"]}}, "h_966": {"id": "h_966", "char": "微", "pinyin": "wēi", "level": 3, "stroke": 13, "example": "微笑", "frequency": 966, "confusingChars": {"easy": ["彳", "山"], "medium": ["徽", "霉"], "hard": ["威", "危"]}}, "h_967": {"id": "h_967", "char": "锡", "pinyin": "xī", "level": 4, "stroke": 13, "example": "锡纸", "frequency": 967, "confusingChars": {"easy": ["金", "易"], "medium": ["踢", "惕"], "hard": ["西", "夕"]}}, "h_968": {"id": "h_968", "char": "瓣", "pinyin": "bàn", "level": 4, "stroke": 19, "example": "花瓣", "frequency": 968, "confusingChars": {"easy": ["辛", "瓜"], "medium": ["辫", "辩"], "hard": ["半", "伴"]}}, "h_969": {"id": "h_969", "char": "辩", "pinyin": "biàn", "level": 4, "stroke": 16, "example": "辩论", "frequency": 969, "confusingChars": {"easy": ["言", "辛"], "medium": ["辨", "辫"], "hard": ["变", "便"]}}, "h_970": {"id": "h_970", "char": "辨", "pinyin": "biàn", "level": 4, "stroke": 16, "example": "分辨", "frequency": 970, "confusingChars": {"easy": ["刀", "辛"], "medium": ["辩", "辫"], "hard": ["变", "便"]}}, "h_971": {"id": "h_971", "char": "辫", "pinyin": "biàn", "level": 4, "stroke": 17, "example": "辫子", "frequency": 971, "confusingChars": {"easy": ["丝", "辛"], "medium": ["辩", "辨"], "hard": ["变", "便"]}}, "h_972": {"id": "h_972", "char": "煮", "pinyin": "zhǔ", "level": 3, "stroke": 12, "example": "煮饭", "frequency": 972, "confusingChars": {"easy": ["火", "者"], "medium": ["著", "都"], "hard": ["主", "注"]}}, "h_973": {"id": "h_973", "char": "蒸", "pinyin": "zhēng", "level": 3, "stroke": 13, "example": "蒸气", "frequency": 973, "confusingChars": {"easy": ["草", "水"], "medium": ["煮", "燕"], "hard": ["争", "正"]}}, "h_974": {"id": "h_974", "char": "炸", "pinyin": "zhá", "level": 3, "stroke": 9, "example": "炸鸡", "frequency": 974, "confusingChars": {"easy": ["火", "乍"], "medium": ["作", "昨"], "hard": ["扎", "闸"]}}, "h_975": {"id": "h_975", "char": "肩", "pinyin": "jiān", "level": 3, "stroke": 8, "example": "肩膀", "frequency": 975, "confusingChars": {"easy": ["月", "户"], "medium": ["背", "肯"], "hard": ["间", "监"]}}, "h_976": {"id": "h_976", "char": "胃", "pinyin": "wèi", "level": 3, "stroke": 9, "example": "胃口", "frequency": 976, "confusingChars": {"easy": ["田", "月"], "medium": ["背", "育"], "hard": ["味", "卫"]}}, "h_977": {"id": "h_977", "char": "肠", "pinyin": "cháng", "level": 3, "stroke": 7, "example": "肠胃", "frequency": 977, "confusingChars": {"easy": ["月", "昜"], "medium": ["杨", "汤"], "hard": ["常", "长"]}}, "h_978": {"id": "h_978", "char": "质", "pinyin": "zhì", "level": 3, "stroke": 8, "example": "质量", "frequency": 978, "confusingChars": {"easy": ["贝", "厂"], "medium": ["盾", "厉"], "hard": ["制", "志"]}}, "h_979": {"id": "h_979", "char": "德", "pinyin": "dé", "level": 3, "stroke": 15, "example": "品德", "frequency": 979, "confusingChars": {"easy": ["心", "彳"], "medium": ["听", "稳"], "hard": ["得", "地"]}}, "h_980": {"id": "h_980", "char": "智", "pinyin": "zhì", "level": 3, "stroke": 12, "example": "智慧", "frequency": 980, "confusingChars": {"easy": ["日", "知"], "medium": ["知", "暂"], "hard": ["知", "制"]}}, "h_981": {"id": "h_981", "char": "塘", "pinyin": "táng", "level": 3, "stroke": 13, "example": "池塘", "frequency": 981, "confusingChars": {"easy": ["土", "唐"], "medium": ["糖", "唐"], "hard": ["糖", "堂"]}}, "h_982": {"id": "h_982", "char": "渠", "pinyin": "qú", "level": 4, "stroke": 11, "example": "水渠", "frequency": 982, "confusingChars": {"easy": ["木", "水"], "medium": ["染", "梁"], "hard": ["局", "曲"]}}, "h_983": {"id": "h_983", "char": "律", "pinyin": "lǜ", "level": 3, "stroke": 9, "example": "法律", "frequency": 983, "confusingChars": {"easy": ["彳", "聿"], "medium": ["津", "建"], "hard": ["绿", "虑"]}}, "h_984": {"id": "h_984", "char": "规", "pinyin": "guī", "level": 3, "stroke": 8, "example": "规则", "frequency": 984, "confusingChars": {"easy": ["见", "夫"], "medium": ["现", "观"], "hard": ["归", "龟"]}}, "h_985": {"id": "h_985", "char": "则", "pinyin": "zé", "level": 3, "stroke": 6, "example": "原则", "frequency": 985, "confusingChars": {"easy": ["贝", "刂"], "medium": ["测", "侧"], "hard": ["责", "泽"]}}, "h_986": {"id": "h_986", "char": "纪", "pinyin": "jì", "level": 3, "stroke": 6, "example": "纪念", "frequency": 986, "confusingChars": {"easy": ["丝", "己"], "medium": ["记", "级"], "hard": ["记", "计"]}}, "h_987": {"id": "h_987", "char": "郊", "pinyin": "jiāo", "level": 3, "stroke": 6, "example": "郊外", "frequency": 987, "confusingChars": {"easy": ["交", "阝"], "medium": ["交", "效"], "hard": ["交", "教"]}}, "h_988": {"id": "h_988", "char": "野", "pinyin": "yě", "level": 3, "stroke": 11, "example": "野外", "frequency": 988, "confusingChars": {"easy": ["里", "予"], "medium": ["墅", "舒"], "hard": ["也", "耶"]}}, "h_989": {"id": "h_989", "char": "县", "pinyin": "xiàn", "level": 3, "stroke": 7, "example": "县城", "frequency": 989, "confusingChars": {"easy": ["目", "且"], "medium": ["具", "悬"], "hard": ["现", "线"]}}, "h_990": {"id": "h_990", "char": "镇", "pinyin": "zhèn", "level": 3, "stroke": 15, "example": "小镇", "frequency": 990, "confusingChars": {"easy": ["金", "真"], "medium": ["慎", "填"], "hard": ["阵", "振"]}}, "h_991": {"id": "h_991", "char": "墨", "pinyin": "mò", "level": 3, "stroke": 15, "example": "墨水", "frequency": 991, "confusingChars": {"easy": ["黑", "土"], "medium": ["黑", "默"], "hard": ["默", "末"]}}, "h_992": {"id": "h_992", "char": "茎", "pinyin": "jīng", "level": 4, "stroke": 8, "example": "根茎", "frequency": 992, "confusingChars": {"easy": ["草", "工"], "medium": ["经", "径"], "hard": ["经", "精"]}}, "h_993": {"id": "h_993", "char": "煎", "pinyin": "jiān", "level": 3, "stroke": 13, "example": "煎蛋", "frequency": 993, "confusingChars": {"easy": ["火", "前"], "medium": ["前", "剪"], "hard": ["间", "尖"]}}, "h_994": {"id": "h_994", "char": "熬", "pinyin": "áo", "level": 4, "stroke": 14, "example": "熬夜", "frequency": 994, "confusingChars": {"easy": ["火", "放"], "medium": ["傲", "遨"], "hard": ["傲", "奥"]}}, "h_995": {"id": "h_995", "char": "剩", "pinyin": "shèng", "level": 3, "stroke": 12, "example": "剩下", "frequency": 995, "confusingChars": {"easy": ["乘", "刂"], "medium": ["乘", "乖"], "hard": ["胜", "盛"]}}, "h_996": {"id": "h_996", "char": "余", "pinyin": "yú", "level": 3, "stroke": 7, "example": "多余", "frequency": 996, "confusingChars": {"easy": ["人", "禾"], "medium": ["除", "涂"], "hard": ["鱼", "于"]}}, "h_997": {"id": "h_997", "char": "缺", "pinyin": "quē", "level": 3, "stroke": 10, "example": "缺点", "frequency": 997, "confusingChars": {"easy": ["缶", "决"], "medium": ["缸", "决"], "hard": ["却", "确"]}}, "h_998": {"id": "h_998", "char": "雹", "pinyin": "báo", "level": 4, "stroke": 13, "example": "冰雹", "frequency": 998, "confusingChars": {"easy": ["雨", "包"], "medium": ["雷", "电"], "hard": ["薄", "抱"]}}, "h_999": {"id": "h_999", "char": "谷", "pinyin": "gǔ", "level": 3, "stroke": 7, "example": "山谷", "frequency": 999, "confusingChars": {"easy": ["八", "人口"], "medium": ["容", "俗"], "hard": ["骨", "鼓"]}}, "h_1000": {"id": "h_1000", "char": "跨", "pinyin": "kuà", "level": 3, "stroke": 13, "example": "跨过", "frequency": 1000, "confusingChars": {"easy": ["足", "大"], "medium": ["路", "夸"], "hard": ["夸", "垮"]}}}